{
	"display_name":"Eagle Eye Upgrade",
	"description":"Your commander becomes specialised in detecting enemies.\n\nGain a 200% increase to base commander sight",
	"stack_limit":5,
	"probability":10,
	"recon":{
		"observer":{
			"items":[
				{
					"layer":"surface_and_air",
					"channel":"sight",
					"shape":"capsule",
					"radius":200
				},
				{
					"layer":"underwater",
					"channel":"sight",
					"shape":"capsule",
					"radius":0
				},
				{
					"layer":"celestial",
					"channel":"sight",
					"shape":"sphere",
					"radius":0
				}
			]
		}
	}
}